web_audio_api-0.1.0.dist-info/METADATA
web_audio_api-0.1.0.dist-info/WHEEL
web_audio_api/__init__.py
web_audio_api/web_audio_api.cpython-312-darwin.so
web_audio_api-0.1.0.dist-info/RECORD
