Metadata-Version: 2.3
Name: web-audio-api
Version: 0.1.0
Classifier: Programming Language :: Rust
Classifier: Topic :: Multimedia :: Sound/Audio
Classifier: Programming Language :: Python :: Implementation :: PyPy
Summary: A Rust/Python implementation of the Web Audio API, for use in non-browser contexts
Keywords: web-audio-api,audio,sound,dsp
License: MIT License
Requires-Python: >=3.8
Project-URL: Repository, https://github.com/orottier/web-audio-api-rs
Project-URL: Issues, https://github.com/orottier/web-audio-api-rs/issues
